{
  "meta": {
    "generatedAt": "2026-06-26T19:21:49.379Z",
    "source": "RSS (BBC/Guardian/Sky)",
    "attribution": "Match data via TheSportsDB (thesportsdb.com). Headlines link to their original publishers."
  },
  "featured": {
    "id": "bbc_sport-0",
    "topic": "News",
    "headline": "Rice back in England training but James misses out again",
    "source": "BBC Sport",
    "timeAgo": "2h",
    "url": "https://www.bbc.co.uk/sport/football/articles/ckg4kv0kkgeo?at_medium=RSS&at_campaign=rss",
    "isFeatured": true,
    "hasAiSummary": false
  },
  "articles": [
    {
      "id": "sky_sports-0",
      "topic": "News Story",
      "headline": "Draper’s Eastbourne run ends in semi-final at hands of Humbert",
      "source": "Sky Sports",
      "timeAgo": "",
      "url": "https://www.skysports.com/tennis/news/12040/13558095/jack-drapers-eastbourne-run-ends-in-semi-final-at-hands-of-ugo-humbert-as-briton-prepares-for-daunting-wimbledon-draw",
      "isFeatured": false,
      "hasAiSummary": false
    },
    {
      "id": "bbc_sport-1",
      "topic": "News",
      "headline": "Why has Trump stayed away from the World Cup?",
      "source": "BBC Sport",
      "timeAgo": "4h",
      "url": "https://www.bbc.co.uk/sport/football/articles/c0myxevn3emo?at_medium=RSS&at_campaign=rss",
      "isFeatured": false,
      "hasAiSummary": false
    },
    {
      "id": "sky_sports-1",
      "topic": "Liveblog",
      "headline": "World Cup latest: Panama team-mates clash in training ahead of England game",
      "source": "Sky Sports",
      "timeAgo": "",
      "url": "https://www.skysports.com/football/live-blog/12040/13509050/world-cup-2026-news-and-live-updates-usa-canada-and-mexico-latest-including-trump-tickets-and-fans",
      "isFeatured": false,
      "hasAiSummary": false
    },
    {
      "id": "bbc_sport-2",
      "topic": "News",
      "headline": "Is a former England striker right about reasons for Scottish football's ills?",
      "source": "BBC Sport",
      "timeAgo": "2h",
      "url": "https://www.bbc.co.uk/sport/football/articles/c5yz9nnp2p1o?at_medium=RSS&at_campaign=rss",
      "isFeatured": false,
      "hasAiSummary": false
    },
    {
      "id": "sky_sports-2",
      "topic": "News Story",
      "headline": "Duckett and Stokes wrestle Trent Bridge Test back England's way",
      "source": "Sky Sports",
      "timeAgo": "",
      "url": "https://www.skysports.com/cricket/news/12040/13558114/england-vs-new-zealand-ben-duckett-and-ben-stokes-carry-hosts-continued-fightback-in-series-decider-at-trent-bridge",
      "isFeatured": false,
      "hasAiSummary": false
    },
    {
      "id": "bbc_sport-3",
      "topic": "News",
      "headline": "Rainbow flags await Egypt and Iran at awkward Pride Match",
      "source": "BBC Sport",
      "timeAgo": "8h",
      "url": "https://www.bbc.co.uk/sport/football/articles/ckg4k0ddg5go?at_medium=RSS&at_campaign=rss",
      "isFeatured": false,
      "hasAiSummary": false
    },
    {
      "id": "sky_sports-3",
      "topic": "Liveblog",
      "headline": "Everton latest: Toffees join race to sign Serie A midfielder",
      "source": "Sky Sports",
      "timeAgo": "",
      "url": "https://www.skysports.com/football/live-blog/12040/13279303/everton-transfers-latest-news-rumours-and-gossip-live-updates-goals-and-highlights",
      "isFeatured": false,
      "hasAiSummary": false
    },
    {
      "id": "bbc_sport-4",
      "topic": "News",
      "headline": "Arsenal explore moves for Newcastle's Guimaraes & Tonali",
      "source": "BBC Sport",
      "timeAgo": "4h",
      "url": "https://www.bbc.co.uk/sport/football/articles/cly71eqgej8o?at_medium=RSS&at_campaign=rss",
      "isFeatured": false,
      "hasAiSummary": false
    },
    {
      "id": "sky_sports-4",
      "topic": "Liveblog",
      "headline": "Dembele fires France ahead against Norway; Senegal lead Iraq LIVE!",
      "source": "Sky Sports",
      "timeAgo": "",
      "url": "https://www.skysports.com/football/norway-vs-france/live/549831",
      "isFeatured": false,
      "hasAiSummary": false
    },
    {
      "id": "bbc_sport-5",
      "topic": "News",
      "headline": "Has VAR become a lottery at the World Cup?",
      "source": "BBC Sport",
      "timeAgo": "6h",
      "url": "https://www.bbc.co.uk/sport/football/articles/c8e2ynrp7kro?at_medium=RSS&at_campaign=rss",
      "isFeatured": false,
      "hasAiSummary": false
    },
    {
      "id": "sky_sports-5",
      "topic": "News Story",
      "headline": "Usyk vacates world titles",
      "source": "Sky Sports",
      "timeAgo": "",
      "url": "https://www.skysports.com/boxing/news/12040/13558107/oleksandr-usyk-vacates-world-titles-but-says-his-last-dance-is-still-to-come",
      "isFeatured": false,
      "hasAiSummary": false
    },
    {
      "id": "bbc_sport-6",
      "topic": "News",
      "headline": "Start Rashford? Bring O'Reilly back? Pick your England XI to face Panama",
      "source": "BBC Sport",
      "timeAgo": "7h",
      "url": "https://www.bbc.co.uk/sport/football/articles/crm0xrg8j4ro?at_medium=RSS&at_campaign=rss",
      "isFeatured": false,
      "hasAiSummary": false
    },
    {
      "id": "sky_sports-6",
      "topic": "News Story",
      "headline": "Antonelli completes Austria Friday double as Russell struggles",
      "source": "Sky Sports",
      "timeAgo": "",
      "url": "https://www.skysports.com/f1/news/12040/13557944/austrian-gp-kimi-antonelli-completes-friday-practice-double-as-mercedes-team-mate-george-russell-struggles",
      "isFeatured": false,
      "hasAiSummary": false
    },
    {
      "id": "bbc_sport-7",
      "topic": "News",
      "headline": "Why there's more to Spain than Lamine Yamal - Azpilicueta",
      "source": "BBC Sport",
      "timeAgo": "6h",
      "url": "https://www.bbc.co.uk/sport/football/articles/cg531yd0ddpo?at_medium=RSS&at_campaign=rss",
      "isFeatured": false,
      "hasAiSummary": false
    },
    {
      "id": "sky_sports-7",
      "topic": "Liveblog",
      "headline": "Hadjar 'surprised' by struggles in upgraded Red Bull",
      "source": "Sky Sports",
      "timeAgo": "",
      "url": "https://www.skysports.com/f1/live-blog/12040/13557410/f1-austrian-gp-live-friday-practice-updates-results-stream-highlights-from-formula-1-race-weekend-at-red-bull-ring",
      "isFeatured": false,
      "hasAiSummary": false
    },
    {
      "id": "bbc_sport-8",
      "topic": "News",
      "headline": "The 0-0 draw that highlighted flaw in World Cup format",
      "source": "BBC Sport",
      "timeAgo": "9h",
      "url": "https://www.bbc.co.uk/sport/football/articles/cgev2vdzjvvo?at_medium=RSS&at_campaign=rss",
      "isFeatured": false,
      "hasAiSummary": false
    },
    {
      "id": "sky_sports-8",
      "topic": "Video",
      "headline": "Afternoon session: Duckett flies to 50 after NZ lose quick wickets",
      "source": "Sky Sports",
      "timeAgo": "",
      "url": "https://www.skysports.com/watch/video/13558068/england-vs-new-zealand-afternoon-session-highlights",
      "isFeatured": false,
      "hasAiSummary": false
    },
    {
      "id": "bbc_sport-9",
      "topic": "News",
      "headline": "Where has it gone wrong for Bielsa's struggling Uruguay?",
      "source": "BBC Sport",
      "timeAgo": "4h",
      "url": "https://www.bbc.co.uk/sport/football/articles/ce95d89x5meo?at_medium=RSS&at_campaign=rss",
      "isFeatured": false,
      "hasAiSummary": false
    },
    {
      "id": "sky_sports-9",
      "topic": "News Story",
      "headline": "Papers: Arsenal preparing second approach for Guimaraes",
      "source": "Sky Sports",
      "timeAgo": "",
      "url": "https://www.skysports.com/football/news/12040/13558113/bruno-guimaraes-transfer-news-arsenal-preparing-second-approach-for-newcastle-captain-paper-talk",
      "isFeatured": false,
      "hasAiSummary": false
    }
  ]
}
