{
  "meta": {
    "generatedAt": "2026-06-30T06:51:50.463Z",
    "source": "RSS (BBC/Guardian/Sky)",
    "attribution": "Match data via TheSportsDB (thesportsdb.com). Headlines link to their original publishers."
  },
  "featured": {
    "id": "bbc_sport-0",
    "topic": "News",
    "headline": "Germany beaten on penalties as Paraguay reach last 16",
    "source": "BBC Sport",
    "timeAgo": "5h",
    "url": "https://www.bbc.co.uk/sport/football/videos/cm20j4m2k3xo?at_medium=RSS&at_campaign=rss",
    "isFeatured": true,
    "hasAiSummary": false
  },
  "articles": [
    {
      "id": "sky_sports-0",
      "topic": "News Story",
      "headline": "England vs NZ player ratings: Archer impresses in Stokes' farewell Test",
      "source": "Sky Sports",
      "timeAgo": "",
      "url": "https://www.skysports.com/cricket/news/12040/13558972/england-vs-new-zealand-third-test-player-ratings-jofra-archer-and-ben-duckett-impress-in-ben-stokes-farewell-test",
      "isFeatured": false,
      "hasAiSummary": false
    },
    {
      "id": "bbc_sport-1",
      "topic": "News",
      "headline": "The end for Nagelsmann? Germany suffer their 'next football nightmare'",
      "source": "BBC Sport",
      "timeAgo": "4h",
      "url": "https://www.bbc.co.uk/sport/football/articles/c992kzk00kzo?at_medium=RSS&at_campaign=rss",
      "isFeatured": false,
      "hasAiSummary": false
    },
    {
      "id": "sky_sports-1",
      "topic": "Video",
      "headline": "Boxing's fastest fighters! BLINK and you will miss knockouts",
      "source": "Sky Sports",
      "timeAgo": "",
      "url": "https://www.skysports.com/watch/video/13557137/boxings-fastest-fighters-blink-and-you-will-miss-knockouts",
      "isFeatured": false,
      "hasAiSummary": false
    },
    {
      "id": "bbc_sport-2",
      "topic": "News",
      "headline": "Emotional Gakpo scores days after loss of unborn son",
      "source": "BBC Sport",
      "timeAgo": "1h",
      "url": "https://www.bbc.co.uk/sport/football/articles/c5yz3yjgp5yo?at_medium=RSS&at_campaign=rss",
      "isFeatured": false,
      "hasAiSummary": false
    },
    {
      "id": "sky_sports-2",
      "topic": "News Story",
      "headline": "Button: Why Hamilton should be confident of Silverstone victory chances",
      "source": "Sky Sports",
      "timeAgo": "",
      "url": "https://www.skysports.com/f1/news/12040/13558996/lewis-hamilton-will-be-confident-of-challenging-for-victory-at-british-gp-says-his-former-team-mate-jenson-button",
      "isFeatured": false,
      "hasAiSummary": false
    },
    {
      "id": "bbc_sport-3",
      "topic": "News",
      "headline": "45 minutes from Brazil 'humiliation' - but 'Crafty Carlo' does it again",
      "source": "BBC Sport",
      "timeAgo": "8h",
      "url": "https://www.bbc.co.uk/sport/football/articles/c17yzyy8ldko?at_medium=RSS&at_campaign=rss",
      "isFeatured": false,
      "hasAiSummary": false
    },
    {
      "id": "sky_sports-3",
      "topic": "News Story",
      "headline": "Today on Sky Sports Racing: Brighton and Ffos Las host live action",
      "source": "Sky Sports",
      "timeAgo": "",
      "url": "https://www.skysports.com/racing/news/12040/13558535/today-on-sky-sports-racing-brighton-and-ffos-las-host-live-action",
      "isFeatured": false,
      "hasAiSummary": false
    },
    {
      "id": "bbc_sport-4",
      "topic": "News",
      "headline": "Inside Paraguay's tears of joy over their seismic World Cup shock",
      "source": "BBC Sport",
      "timeAgo": "3h",
      "url": "https://www.bbc.co.uk/sport/football/articles/cy5v96vk1q9o?at_medium=RSS&at_campaign=rss",
      "isFeatured": false,
      "hasAiSummary": false
    },
    {
      "id": "sky_sports-4",
      "topic": "Report",
      "headline": "Morocco beat Netherlands in dramatic penalty shoot-out",
      "source": "Sky Sports",
      "timeAgo": "",
      "url": "https://www.skysports.com/football/netherlands-vs-morocco/report/549841",
      "isFeatured": false,
      "hasAiSummary": false
    },
    {
      "id": "bbc_sport-5",
      "topic": "News",
      "headline": "'A joke' - how a 'terrible' VAR disallowed goal cost Germany",
      "source": "BBC Sport",
      "timeAgo": "5h",
      "url": "https://www.bbc.co.uk/sport/football/articles/cm2dy359e8yo?at_medium=RSS&at_campaign=rss",
      "isFeatured": false,
      "hasAiSummary": false
    },
    {
      "id": "sky_sports-5",
      "topic": "Video",
      "headline": "Serena Williams makes her Wimbledon return | Everything you need to know ...",
      "source": "Sky Sports",
      "timeAgo": "",
      "url": "https://www.skysports.com/watch/video/13559027/everything-you-need-to-know-about-serena-williams-ahead-of-wimbledon-return",
      "isFeatured": false,
      "hasAiSummary": false
    },
    {
      "id": "bbc_sport-6",
      "topic": "News",
      "headline": "Who am I? Guess World Cup star No 23",
      "source": "BBC Sport",
      "timeAgo": "1h",
      "url": "https://www.bbc.co.uk/sport/football/articles/c4g85gg5128o?at_medium=RSS&at_campaign=rss",
      "isFeatured": false,
      "hasAiSummary": false
    },
    {
      "id": "sky_sports-6",
      "topic": "Report",
      "headline": "Germany crash out of World Cup on penalties to Paraguay",
      "source": "Sky Sports",
      "timeAgo": "",
      "url": "https://www.skysports.com/football/germany-vs-paraguay/report/549840",
      "isFeatured": false,
      "hasAiSummary": false
    },
    {
      "id": "bbc_sport-7",
      "topic": "News",
      "headline": "Why Maresca? What Man City fans can expect from Guardiola's successor",
      "source": "BBC Sport",
      "timeAgo": "14h",
      "url": "https://www.bbc.co.uk/sport/football/articles/c2k248wwk74o?at_medium=RSS&at_campaign=rss",
      "isFeatured": false,
      "hasAiSummary": false
    },
    {
      "id": "sky_sports-7",
      "topic": "Video",
      "headline": "Madueke’s wholesome reaction to Arsenal teammate Martinelli’s winner!",
      "source": "Sky Sports",
      "timeAgo": "",
      "url": "https://www.skysports.com/watch/video/13559028/brazil-vs-japan-noni-madueke-reacts-to-arsenal-teammate-gabriel-martinellis-winning-goal",
      "isFeatured": false,
      "hasAiSummary": false
    },
    {
      "id": "bbc_sport-8",
      "topic": "News",
      "headline": "How Tuchel is still searching for solutions out wide - Shearer",
      "source": "BBC Sport",
      "timeAgo": "19h",
      "url": "https://www.bbc.co.uk/sport/football/articles/cqj1g9egd80o?at_medium=RSS&at_campaign=rss",
      "isFeatured": false,
      "hasAiSummary": false
    },
    {
      "id": "sky_sports-8",
      "topic": "News Story",
      "headline": "Djokovic and Sinner survive Wimbledon first-round scares",
      "source": "Sky Sports",
      "timeAgo": "",
      "url": "https://www.skysports.com/tennis/news/12040/13558903/wimbledon-novak-djokovic-and-jannik-sinner-survive-scares-while-aryna-sabalenka-strolls-into-second-round",
      "isFeatured": false,
      "hasAiSummary": false
    },
    {
      "id": "bbc_sport-9",
      "topic": "News",
      "headline": "Netherlands crumble in penalty shootout as Morocco reach last 16",
      "source": "BBC Sport",
      "timeAgo": "1h",
      "url": "https://www.bbc.co.uk/sport/football/videos/c4gy5gmd7mjo?at_medium=RSS&at_campaign=rss",
      "isFeatured": false,
      "hasAiSummary": false
    },
    {
      "id": "sky_sports-9",
      "topic": "News Story",
      "headline": "Gardner: Australia must be wary of Matthews in T20 World Cup semi-final",
      "source": "Sky Sports",
      "timeAgo": "",
      "url": "https://www.skysports.com/cricket/news/12040/13559035/icc-womens-t20-world-cup-ashleigh-gardner-says-australia-must-be-wary-of-west-indies-captain-hayley-matthews-firepower-in-semi-final",
      "isFeatured": false,
      "hasAiSummary": false
    }
  ]
}
